{"sante001": 2.0, "cecib001": 1.0, "chatt001": 1.125, "carmf001": 2.0, "carrc003": 1.0, "beckj002": 1.0, "takah001": 3.0, "whita001": 1.0, "hared001": 2.0, "bellt002": 2, "pinej001": 1.6666666666666667, "dankj001": 1, "hudst001": 1.0, "hanst001": 1.0, "lowed001": 1.0, "cahit001": 2.0, "balfg001": 1.0, "colob001": 1, "jepsk001": 1, "weavj003": 1.5, "waldj001": 3, "marqj001": 1, "balec001": 1, "mattr001": 1, "kersc001": 1.0, "billc001": 1.0, "furbc001": 1.0, "cokep001": 1, "kohnm001": 2.0, "pennb002": 1, "beavb001": 2.0, "wrigj001": 1, "pauld001": 1, "pinem001": 2.0, "ray-c001": 1, "hernf002": 1.0, "holld003": 1.0, "duenb001": 1.5, "bakes002": 1, "ramih002": 1, "lirif001": 1.0, "thomr006": 2.0, "ogana001": 1, "uehak001": 1, "adamm001": 1, "reyej003": 2.0, "eyrew001": 1, "gregk001": 1, "huntt002": 1, "matub001": 1.0, "bergb002": 1, "willj003": 5.0, "buehm001": 1.0, "stewz001": 1.0, "dumap001": 2, "slowk001": 1.0, "vasqa001": 2.0, "noesh001": 1.0, "kontg001": 1, "garcf002": 2.0, "gonzg003": 1, "moscg001": 1.0, "hardr001": 2.0, "richg002": 1.0}