{"wallj002": 1, "koeht001": 1, "corbp001": 1, "ryu-h001": 1, "rodrp001": 2, "burgh001": 1, "delae002": 2, "mills001": 1, "nolar001": 1, "richc002": 2, "villc001": 1, "lohsk001": 2, "greiz001": 1, "thayd001": 1, "leroc001": 1, "volqe001": 1, "lillt001": 2, "sancj002": 1, "arrob001": 1, "cahit001": 1, "marqj001": 1, "kellj001": 1, "bellh001": 2, "billc001": 1, "axfoj001": 2, "bowdm001": 1, "mansj001": 1, "torrc001": 1, "magim001": 2, "hawkl001": 1, "jansk001": 1, "kersc001": 1, "luekj001": 1, "stule002": 1, "nicaj001": 1, "wooda002": 1, "mujie001": 1, "gearc001": 1, "mccab001": 1, "milew001": 1, "partc001": 1, "petta001": 1, "leagb001": 3, "peavj001": 1, "carpd001": 1, "tehej001": 1, "guerm001": 2, "jacke001": 2, "bumgm001": 1, "linct001": 1, "withc001": 3, "lee-c003": 1, "kenni001": 1, "slowk001": 1, "moylp001": 1, "belir001": 1, "fifes001": 2, "howej003": 2, "delaj001": 1, "carmf001": 1, "rosst001": 1, "delgr001": 4, "mchuc001": 2, "lackj001": 1, "kickm001": 2, "kontg001": 1, "beckj002": 4, "ottaa001": 1, "bassa001": 2, "fernj003": 1, "collj001": 1, "capuc001": 2, "blanj001": 1, "bailh001": 1, "mahop002": 1, "garco001": 1, "garcf002": 2}